[
    {
        "id": 2803427918,
        "node_id": "MDEyOkxhYmVsZWRFdmVudDI4MDM0Mjc5MTg=",
        "url": "https://api.github.com/repos/microsoft/onnxruntime/issues/events/2803427918",
        "actor": {
            "login": "faxu",
            "id": 20780999,
            "node_id": "MDQ6VXNlcjIwNzgwOTk5",
            "avatar_url": "https://avatars.githubusercontent.com/u/20780999?v=4",
            "gravatar_id": "",
            "url": "https://api.github.com/users/faxu",
            "html_url": "https://github.com/faxu",
            "followers_url": "https://api.github.com/users/faxu/followers",
            "following_url": "https://api.github.com/users/faxu/following{/other_user}",
            "gists_url": "https://api.github.com/users/faxu/gists{/gist_id}",
            "starred_url": "https://api.github.com/users/faxu/starred{/owner}{/repo}",
            "subscriptions_url": "https://api.github.com/users/faxu/subscriptions",
            "organizations_url": "https://api.github.com/users/faxu/orgs",
            "repos_url": "https://api.github.com/users/faxu/repos",
            "events_url": "https://api.github.com/users/faxu/events{/privacy}",
            "received_events_url": "https://api.github.com/users/faxu/received_events",
            "type": "User",
            "site_admin": true
        },
        "event": "labeled",
        "commit_id": null,
        "commit_url": null,
        "created_at": "2019-11-15T17:32:16Z",
        "label": {
            "name": "bug",
            "color": "d73a4a"
        },
        "performed_via_github_app": null
    },
    {
        "id": 2803507216,
        "node_id": "MDEzOkFzc2lnbmVkRXZlbnQyODAzNTA3MjE2",
        "url": "https://api.github.com/repos/microsoft/onnxruntime/issues/events/2803507216",
        "actor": {
            "login": "yuslepukhin",
            "id": 11303988,
            "node_id": "MDQ6VXNlcjExMzAzOTg4",
            "avatar_url": "https://avatars.githubusercontent.com/u/11303988?v=4",
            "gravatar_id": "",
            "url": "https://api.github.com/users/yuslepukhin",
            "html_url": "https://github.com/yuslepukhin",
            "followers_url": "https://api.github.com/users/yuslepukhin/followers",
            "following_url": "https://api.github.com/users/yuslepukhin/following{/other_user}",
            "gists_url": "https://api.github.com/users/yuslepukhin/gists{/gist_id}",
            "starred_url": "https://api.github.com/users/yuslepukhin/starred{/owner}{/repo}",
            "subscriptions_url": "https://api.github.com/users/yuslepukhin/subscriptions",
            "organizations_url": "https://api.github.com/users/yuslepukhin/orgs",
            "repos_url": "https://api.github.com/users/yuslepukhin/repos",
            "events_url": "https://api.github.com/users/yuslepukhin/events{/privacy}",
            "received_events_url": "https://api.github.com/users/yuslepukhin/received_events",
            "type": "User",
            "site_admin": false
        },
        "event": "assigned",
        "commit_id": null,
        "commit_url": null,
        "created_at": "2019-11-15T18:01:40Z",
        "assignee": {
            "login": "yuslepukhin",
            "id": 11303988,
            "node_id": "MDQ6VXNlcjExMzAzOTg4",
            "avatar_url": "https://avatars.githubusercontent.com/u/11303988?v=4",
            "gravatar_id": "",
            "url": "https://api.github.com/users/yuslepukhin",
            "html_url": "https://github.com/yuslepukhin",
            "followers_url": "https://api.github.com/users/yuslepukhin/followers",
            "following_url": "https://api.github.com/users/yuslepukhin/following{/other_user}",
            "gists_url": "https://api.github.com/users/yuslepukhin/gists{/gist_id}",
            "starred_url": "https://api.github.com/users/yuslepukhin/starred{/owner}{/repo}",
            "subscriptions_url": "https://api.github.com/users/yuslepukhin/subscriptions",
            "organizations_url": "https://api.github.com/users/yuslepukhin/orgs",
            "repos_url": "https://api.github.com/users/yuslepukhin/repos",
            "events_url": "https://api.github.com/users/yuslepukhin/events{/privacy}",
            "received_events_url": "https://api.github.com/users/yuslepukhin/received_events",
            "type": "User",
            "site_admin": false
        },
        "performed_via_github_app": null
    },
    {
        "url": "https://api.github.com/repos/microsoft/onnxruntime/issues/comments/554471149",
        "html_url": "https://github.com/microsoft/onnxruntime/issues/2384#issuecomment-554471149",
        "issue_url": "https://api.github.com/repos/microsoft/onnxruntime/issues/2384",
        "id": 554471149,
        "node_id": "MDEyOklzc3VlQ29tbWVudDU1NDQ3MTE0OQ==",
        "user": {
            "login": "yuslepukhin",
            "id": 11303988,
            "node_id": "MDQ6VXNlcjExMzAzOTg4",
            "avatar_url": "https://avatars.githubusercontent.com/u/11303988?v=4",
            "gravatar_id": "",
            "url": "https://api.github.com/users/yuslepukhin",
            "html_url": "https://github.com/yuslepukhin",
            "followers_url": "https://api.github.com/users/yuslepukhin/followers",
            "following_url": "https://api.github.com/users/yuslepukhin/following{/other_user}",
            "gists_url": "https://api.github.com/users/yuslepukhin/gists{/gist_id}",
            "starred_url": "https://api.github.com/users/yuslepukhin/starred{/owner}{/repo}",
            "subscriptions_url": "https://api.github.com/users/yuslepukhin/subscriptions",
            "organizations_url": "https://api.github.com/users/yuslepukhin/orgs",
            "repos_url": "https://api.github.com/users/yuslepukhin/repos",
            "events_url": "https://api.github.com/users/yuslepukhin/events{/privacy}",
            "received_events_url": "https://api.github.com/users/yuslepukhin/received_events",
            "type": "User",
            "site_admin": false
        },
        "created_at": "2019-11-15T18:17:02Z",
        "updated_at": "2019-11-15T18:17:02Z",
        "author_association": "MEMBER",
        "body": "The problem seems to be benign at present because in all of the places where the function is used there are incoming Tensor ORT_ENFORCE where it checks that the number of dimensions is greater than zero. I will fix this though.\r\n@atp798 Do you have a specific example where this causes a crash?",
        "reactions": {
            "url": "https://api.github.com/repos/microsoft/onnxruntime/issues/comments/554471149/reactions",
            "total_count": 0,
            "+1": 0,
            "-1": 0,
            "laugh": 0,
            "hooray": 0,
            "confused": 0,
            "heart": 0,
            "rocket": 0,
            "eyes": 0
        },
        "performed_via_github_app": null,
        "event": "commented",
        "actor": {
            "login": "yuslepukhin",
            "id": 11303988,
            "node_id": "MDQ6VXNlcjExMzAzOTg4",
            "avatar_url": "https://avatars.githubusercontent.com/u/11303988?v=4",
            "gravatar_id": "",
            "url": "https://api.github.com/users/yuslepukhin",
            "html_url": "https://github.com/yuslepukhin",
            "followers_url": "https://api.github.com/users/yuslepukhin/followers",
            "following_url": "https://api.github.com/users/yuslepukhin/following{/other_user}",
            "gists_url": "https://api.github.com/users/yuslepukhin/gists{/gist_id}",
            "starred_url": "https://api.github.com/users/yuslepukhin/starred{/owner}{/repo}",
            "subscriptions_url": "https://api.github.com/users/yuslepukhin/subscriptions",
            "organizations_url": "https://api.github.com/users/yuslepukhin/orgs",
            "repos_url": "https://api.github.com/users/yuslepukhin/repos",
            "events_url": "https://api.github.com/users/yuslepukhin/events{/privacy}",
            "received_events_url": "https://api.github.com/users/yuslepukhin/received_events",
            "type": "User",
            "site_admin": false
        }
    },
    {
        "id": 2803547613,
        "node_id": "MDE0Ok1lbnRpb25lZEV2ZW50MjgwMzU0NzYxMw==",
        "url": "https://api.github.com/repos/microsoft/onnxruntime/issues/events/2803547613",
        "actor": {
            "login": "atp798",
            "id": 14136352,
            "node_id": "MDQ6VXNlcjE0MTM2MzUy",
            "avatar_url": "https://avatars.githubusercontent.com/u/14136352?v=4",
            "gravatar_id": "",
            "url": "https://api.github.com/users/atp798",
            "html_url": "https://github.com/atp798",
            "followers_url": "https://api.github.com/users/atp798/followers",
            "following_url": "https://api.github.com/users/atp798/following{/other_user}",
            "gists_url": "https://api.github.com/users/atp798/gists{/gist_id}",
            "starred_url": "https://api.github.com/users/atp798/starred{/owner}{/repo}",
            "subscriptions_url": "https://api.github.com/users/atp798/subscriptions",
            "organizations_url": "https://api.github.com/users/atp798/orgs",
            "repos_url": "https://api.github.com/users/atp798/repos",
            "events_url": "https://api.github.com/users/atp798/events{/privacy}",
            "received_events_url": "https://api.github.com/users/atp798/received_events",
            "type": "User",
            "site_admin": false
        },
        "event": "mentioned",
        "commit_id": null,
        "commit_url": null,
        "created_at": "2019-11-15T18:17:02Z",
        "performed_via_github_app": null
    },
    {
        "id": 2803547618,
        "node_id": "MDE1OlN1YnNjcmliZWRFdmVudDI4MDM1NDc2MTg=",
        "url": "https://api.github.com/repos/microsoft/onnxruntime/issues/events/2803547618",
        "actor": {
            "login": "atp798",
            "id": 14136352,
            "node_id": "MDQ6VXNlcjE0MTM2MzUy",
            "avatar_url": "https://avatars.githubusercontent.com/u/14136352?v=4",
            "gravatar_id": "",
            "url": "https://api.github.com/users/atp798",
            "html_url": "https://github.com/atp798",
            "followers_url": "https://api.github.com/users/atp798/followers",
            "following_url": "https://api.github.com/users/atp798/following{/other_user}",
            "gists_url": "https://api.github.com/users/atp798/gists{/gist_id}",
            "starred_url": "https://api.github.com/users/atp798/starred{/owner}{/repo}",
            "subscriptions_url": "https://api.github.com/users/atp798/subscriptions",
            "organizations_url": "https://api.github.com/users/atp798/orgs",
            "repos_url": "https://api.github.com/users/atp798/repos",
            "events_url": "https://api.github.com/users/atp798/events{/privacy}",
            "received_events_url": "https://api.github.com/users/atp798/received_events",
            "type": "User",
            "site_admin": false
        },
        "event": "subscribed",
        "commit_id": null,
        "commit_url": null,
        "created_at": "2019-11-15T18:17:02Z",
        "performed_via_github_app": null
    },
    {
        "url": "https://api.github.com/repos/microsoft/onnxruntime/issues/comments/554476434",
        "html_url": "https://github.com/microsoft/onnxruntime/issues/2384#issuecomment-554476434",
        "issue_url": "https://api.github.com/repos/microsoft/onnxruntime/issues/2384",
        "id": 554476434,
        "node_id": "MDEyOklzc3VlQ29tbWVudDU1NDQ3NjQzNA==",
        "user": {
            "login": "yuslepukhin",
            "id": 11303988,
            "node_id": "MDQ6VXNlcjExMzAzOTg4",
            "avatar_url": "https://avatars.githubusercontent.com/u/11303988?v=4",
            "gravatar_id": "",
            "url": "https://api.github.com/users/yuslepukhin",
            "html_url": "https://github.com/yuslepukhin",
            "followers_url": "https://api.github.com/users/yuslepukhin/followers",
            "following_url": "https://api.github.com/users/yuslepukhin/following{/other_user}",
            "gists_url": "https://api.github.com/users/yuslepukhin/gists{/gist_id}",
            "starred_url": "https://api.github.com/users/yuslepukhin/starred{/owner}{/repo}",
            "subscriptions_url": "https://api.github.com/users/yuslepukhin/subscriptions",
            "organizations_url": "https://api.github.com/users/yuslepukhin/orgs",
            "repos_url": "https://api.github.com/users/yuslepukhin/repos",
            "events_url": "https://api.github.com/users/yuslepukhin/events{/privacy}",
            "received_events_url": "https://api.github.com/users/yuslepukhin/received_events",
            "type": "User",
            "site_admin": false
        },
        "created_at": "2019-11-15T18:31:46Z",
        "updated_at": "2019-11-15T18:31:46Z",
        "author_association": "MEMBER",
        "body": "The problem seems to be widespread due to https://github.com/microsoft/onnxruntime/pull/2217",
        "reactions": {
            "url": "https://api.github.com/repos/microsoft/onnxruntime/issues/comments/554476434/reactions",
            "total_count": 0,
            "+1": 0,
            "-1": 0,
            "laugh": 0,
            "hooray": 0,
            "confused": 0,
            "heart": 0,
            "rocket": 0,
            "eyes": 0
        },
        "performed_via_github_app": null,
        "event": "commented",
        "actor": {
            "login": "yuslepukhin",
            "id": 11303988,
            "node_id": "MDQ6VXNlcjExMzAzOTg4",
            "avatar_url": "https://avatars.githubusercontent.com/u/11303988?v=4",
            "gravatar_id": "",
            "url": "https://api.github.com/users/yuslepukhin",
            "html_url": "https://github.com/yuslepukhin",
            "followers_url": "https://api.github.com/users/yuslepukhin/followers",
            "following_url": "https://api.github.com/users/yuslepukhin/following{/other_user}",
            "gists_url": "https://api.github.com/users/yuslepukhin/gists{/gist_id}",
            "starred_url": "https://api.github.com/users/yuslepukhin/starred{/owner}{/repo}",
            "subscriptions_url": "https://api.github.com/users/yuslepukhin/subscriptions",
            "organizations_url": "https://api.github.com/users/yuslepukhin/orgs",
            "repos_url": "https://api.github.com/users/yuslepukhin/repos",
            "events_url": "https://api.github.com/users/yuslepukhin/events{/privacy}",
            "received_events_url": "https://api.github.com/users/yuslepukhin/received_events",
            "type": "User",
            "site_admin": false
        }
    },
    {
        "id": 2803594357,
        "node_id": "MDEzOkFzc2lnbmVkRXZlbnQyODAzNTk0MzU3",
        "url": "https://api.github.com/repos/microsoft/onnxruntime/issues/events/2803594357",
        "actor": {
            "login": "yuslepukhin",
            "id": 11303988,
            "node_id": "MDQ6VXNlcjExMzAzOTg4",
            "avatar_url": "https://avatars.githubusercontent.com/u/11303988?v=4",
            "gravatar_id": "",
            "url": "https://api.github.com/users/yuslepukhin",
            "html_url": "https://github.com/yuslepukhin",
            "followers_url": "https://api.github.com/users/yuslepukhin/followers",
            "following_url": "https://api.github.com/users/yuslepukhin/following{/other_user}",
            "gists_url": "https://api.github.com/users/yuslepukhin/gists{/gist_id}",
            "starred_url": "https://api.github.com/users/yuslepukhin/starred{/owner}{/repo}",
            "subscriptions_url": "https://api.github.com/users/yuslepukhin/subscriptions",
            "organizations_url": "https://api.github.com/users/yuslepukhin/orgs",
            "repos_url": "https://api.github.com/users/yuslepukhin/repos",
            "events_url": "https://api.github.com/users/yuslepukhin/events{/privacy}",
            "received_events_url": "https://api.github.com/users/yuslepukhin/received_events",
            "type": "User",
            "site_admin": false
        },
        "event": "assigned",
        "commit_id": null,
        "commit_url": null,
        "created_at": "2019-11-15T18:34:51Z",
        "assignee": {
            "login": "skottmckay",
            "id": 979079,
            "node_id": "MDQ6VXNlcjk3OTA3OQ==",
            "avatar_url": "https://avatars.githubusercontent.com/u/979079?v=4",
            "gravatar_id": "",
            "url": "https://api.github.com/users/skottmckay",
            "html_url": "https://github.com/skottmckay",
            "followers_url": "https://api.github.com/users/skottmckay/followers",
            "following_url": "https://api.github.com/users/skottmckay/following{/other_user}",
            "gists_url": "https://api.github.com/users/skottmckay/gists{/gist_id}",
            "starred_url": "https://api.github.com/users/skottmckay/starred{/owner}{/repo}",
            "subscriptions_url": "https://api.github.com/users/skottmckay/subscriptions",
            "organizations_url": "https://api.github.com/users/skottmckay/orgs",
            "repos_url": "https://api.github.com/users/skottmckay/repos",
            "events_url": "https://api.github.com/users/skottmckay/events{/privacy}",
            "received_events_url": "https://api.github.com/users/skottmckay/received_events",
            "type": "User",
            "site_admin": false
        },
        "performed_via_github_app": null
    },
    {
        "id": 2803595018,
        "node_id": "MDE1OlVuYXNzaWduZWRFdmVudDI4MDM1OTUwMTg=",
        "url": "https://api.github.com/repos/microsoft/onnxruntime/issues/events/2803595018",
        "actor": {
            "login": "yuslepukhin",
            "id": 11303988,
            "node_id": "MDQ6VXNlcjExMzAzOTg4",
            "avatar_url": "https://avatars.githubusercontent.com/u/11303988?v=4",
            "gravatar_id": "",
            "url": "https://api.github.com/users/yuslepukhin",
            "html_url": "https://github.com/yuslepukhin",
            "followers_url": "https://api.github.com/users/yuslepukhin/followers",
            "following_url": "https://api.github.com/users/yuslepukhin/following{/other_user}",
            "gists_url": "https://api.github.com/users/yuslepukhin/gists{/gist_id}",
            "starred_url": "https://api.github.com/users/yuslepukhin/starred{/owner}{/repo}",
            "subscriptions_url": "https://api.github.com/users/yuslepukhin/subscriptions",
            "organizations_url": "https://api.github.com/users/yuslepukhin/orgs",
            "repos_url": "https://api.github.com/users/yuslepukhin/repos",
            "events_url": "https://api.github.com/users/yuslepukhin/events{/privacy}",
            "received_events_url": "https://api.github.com/users/yuslepukhin/received_events",
            "type": "User",
            "site_admin": false
        },
        "event": "unassigned",
        "commit_id": null,
        "commit_url": null,
        "created_at": "2019-11-15T18:35:07Z",
        "assignee": {
            "login": "yuslepukhin",
            "id": 11303988,
            "node_id": "MDQ6VXNlcjExMzAzOTg4",
            "avatar_url": "https://avatars.githubusercontent.com/u/11303988?v=4",
            "gravatar_id": "",
            "url": "https://api.github.com/users/yuslepukhin",
            "html_url": "https://github.com/yuslepukhin",
            "followers_url": "https://api.github.com/users/yuslepukhin/followers",
            "following_url": "https://api.github.com/users/yuslepukhin/following{/other_user}",
            "gists_url": "https://api.github.com/users/yuslepukhin/gists{/gist_id}",
            "starred_url": "https://api.github.com/users/yuslepukhin/starred{/owner}{/repo}",
            "subscriptions_url": "https://api.github.com/users/yuslepukhin/subscriptions",
            "organizations_url": "https://api.github.com/users/yuslepukhin/orgs",
            "repos_url": "https://api.github.com/users/yuslepukhin/repos",
            "events_url": "https://api.github.com/users/yuslepukhin/events{/privacy}",
            "received_events_url": "https://api.github.com/users/yuslepukhin/received_events",
            "type": "User",
            "site_admin": false
        },
        "performed_via_github_app": null
    },
    {
        "url": "https://api.github.com/repos/microsoft/onnxruntime/issues/comments/554546847",
        "html_url": "https://github.com/microsoft/onnxruntime/issues/2384#issuecomment-554546847",
        "issue_url": "https://api.github.com/repos/microsoft/onnxruntime/issues/2384",
        "id": 554546847,
        "node_id": "MDEyOklzc3VlQ29tbWVudDU1NDU0Njg0Nw==",
        "user": {
            "login": "pranavsharma",
            "id": 2732907,
            "node_id": "MDQ6VXNlcjI3MzI5MDc=",
            "avatar_url": "https://avatars.githubusercontent.com/u/2732907?v=4",
            "gravatar_id": "",
            "url": "https://api.github.com/users/pranavsharma",
            "html_url": "https://github.com/pranavsharma",
            "followers_url": "https://api.github.com/users/pranavsharma/followers",
            "following_url": "https://api.github.com/users/pranavsharma/following{/other_user}",
            "gists_url": "https://api.github.com/users/pranavsharma/gists{/gist_id}",
            "starred_url": "https://api.github.com/users/pranavsharma/starred{/owner}{/repo}",
            "subscriptions_url": "https://api.github.com/users/pranavsharma/subscriptions",
            "organizations_url": "https://api.github.com/users/pranavsharma/orgs",
            "repos_url": "https://api.github.com/users/pranavsharma/repos",
            "events_url": "https://api.github.com/users/pranavsharma/events{/privacy}",
            "received_events_url": "https://api.github.com/users/pranavsharma/received_events",
            "type": "User",
            "site_admin": false
        },
        "created_at": "2019-11-15T22:04:13Z",
        "updated_at": "2019-11-15T22:04:13Z",
        "author_association": "MEMBER",
        "body": "input_shape.Size() can return -1 as well to represent symbolic shapes. Check tensor_shape.cc.\r\n\r\n",
        "reactions": {
            "url": "https://api.github.com/repos/microsoft/onnxruntime/issues/comments/554546847/reactions",
            "total_count": 0,
            "+1": 0,
            "-1": 0,
            "laugh": 0,
            "hooray": 0,
            "confused": 0,
            "heart": 0,
            "rocket": 0,
            "eyes": 0
        },
        "performed_via_github_app": null,
        "event": "commented",
        "actor": {
            "login": "pranavsharma",
            "id": 2732907,
            "node_id": "MDQ6VXNlcjI3MzI5MDc=",
            "avatar_url": "https://avatars.githubusercontent.com/u/2732907?v=4",
            "gravatar_id": "",
            "url": "https://api.github.com/users/pranavsharma",
            "html_url": "https://github.com/pranavsharma",
            "followers_url": "https://api.github.com/users/pranavsharma/followers",
            "following_url": "https://api.github.com/users/pranavsharma/following{/other_user}",
            "gists_url": "https://api.github.com/users/pranavsharma/gists{/gist_id}",
            "starred_url": "https://api.github.com/users/pranavsharma/starred{/owner}{/repo}",
            "subscriptions_url": "https://api.github.com/users/pranavsharma/subscriptions",
            "organizations_url": "https://api.github.com/users/pranavsharma/orgs",
            "repos_url": "https://api.github.com/users/pranavsharma/repos",
            "events_url": "https://api.github.com/users/pranavsharma/events{/privacy}",
            "received_events_url": "https://api.github.com/users/pranavsharma/received_events",
            "type": "User",
            "site_admin": false
        }
    },
    {
        "url": "https://api.github.com/repos/microsoft/onnxruntime/issues/comments/554548503",
        "html_url": "https://github.com/microsoft/onnxruntime/issues/2384#issuecomment-554548503",
        "issue_url": "https://api.github.com/repos/microsoft/onnxruntime/issues/2384",
        "id": 554548503,
        "node_id": "MDEyOklzc3VlQ29tbWVudDU1NDU0ODUwMw==",
        "user": {
            "login": "skottmckay",
            "id": 979079,
            "node_id": "MDQ6VXNlcjk3OTA3OQ==",
            "avatar_url": "https://avatars.githubusercontent.com/u/979079?v=4",
            "gravatar_id": "",
            "url": "https://api.github.com/users/skottmckay",
            "html_url": "https://github.com/skottmckay",
            "followers_url": "https://api.github.com/users/skottmckay/followers",
            "following_url": "https://api.github.com/users/skottmckay/following{/other_user}",
            "gists_url": "https://api.github.com/users/skottmckay/gists{/gist_id}",
            "starred_url": "https://api.github.com/users/skottmckay/starred{/owner}{/repo}",
            "subscriptions_url": "https://api.github.com/users/skottmckay/subscriptions",
            "organizations_url": "https://api.github.com/users/skottmckay/orgs",
            "repos_url": "https://api.github.com/users/skottmckay/repos",
            "events_url": "https://api.github.com/users/skottmckay/events{/privacy}",
            "received_events_url": "https://api.github.com/users/skottmckay/received_events",
            "type": "User",
            "site_admin": false
        },
        "created_at": "2019-11-15T22:09:01Z",
        "updated_at": "2019-11-15T22:09:01Z",
        "author_association": "MEMBER",
        "body": "Size() returns 1 if there are no dims. It only returns 0 if one or more dims have a value of 0. ",
        "reactions": {
            "url": "https://api.github.com/repos/microsoft/onnxruntime/issues/comments/554548503/reactions",
            "total_count": 0,
            "+1": 0,
            "-1": 0,
            "laugh": 0,
            "hooray": 0,
            "confused": 0,
            "heart": 0,
            "rocket": 0,
            "eyes": 0
        },
        "performed_via_github_app": null,
        "event": "commented",
        "actor": {
            "login": "skottmckay",
            "id": 979079,
            "node_id": "MDQ6VXNlcjk3OTA3OQ==",
            "avatar_url": "https://avatars.githubusercontent.com/u/979079?v=4",
            "gravatar_id": "",
            "url": "https://api.github.com/users/skottmckay",
            "html_url": "https://github.com/skottmckay",
            "followers_url": "https://api.github.com/users/skottmckay/followers",
            "following_url": "https://api.github.com/users/skottmckay/following{/other_user}",
            "gists_url": "https://api.github.com/users/skottmckay/gists{/gist_id}",
            "starred_url": "https://api.github.com/users/skottmckay/starred{/owner}{/repo}",
            "subscriptions_url": "https://api.github.com/users/skottmckay/subscriptions",
            "organizations_url": "https://api.github.com/users/skottmckay/orgs",
            "repos_url": "https://api.github.com/users/skottmckay/repos",
            "events_url": "https://api.github.com/users/skottmckay/events{/privacy}",
            "received_events_url": "https://api.github.com/users/skottmckay/received_events",
            "type": "User",
            "site_admin": false
        }
    },
    {
        "url": "https://api.github.com/repos/microsoft/onnxruntime/issues/comments/554612289",
        "html_url": "https://github.com/microsoft/onnxruntime/issues/2384#issuecomment-554612289",
        "issue_url": "https://api.github.com/repos/microsoft/onnxruntime/issues/2384",
        "id": 554612289,
        "node_id": "MDEyOklzc3VlQ29tbWVudDU1NDYxMjI4OQ==",
        "user": {
            "login": "atp798",
            "id": 14136352,
            "node_id": "MDQ6VXNlcjE0MTM2MzUy",
            "avatar_url": "https://avatars.githubusercontent.com/u/14136352?v=4",
            "gravatar_id": "",
            "url": "https://api.github.com/users/atp798",
            "html_url": "https://github.com/atp798",
            "followers_url": "https://api.github.com/users/atp798/followers",
            "following_url": "https://api.github.com/users/atp798/following{/other_user}",
            "gists_url": "https://api.github.com/users/atp798/gists{/gist_id}",
            "starred_url": "https://api.github.com/users/atp798/starred{/owner}{/repo}",
            "subscriptions_url": "https://api.github.com/users/atp798/subscriptions",
            "organizations_url": "https://api.github.com/users/atp798/orgs",
            "repos_url": "https://api.github.com/users/atp798/repos",
            "events_url": "https://api.github.com/users/atp798/events{/privacy}",
            "received_events_url": "https://api.github.com/users/atp798/received_events",
            "type": "User",
            "site_admin": false
        },
        "created_at": "2019-11-16T07:14:35Z",
        "updated_at": "2019-11-16T07:20:40Z",
        "author_association": "NONE",
        "body": "> The problem seems to be benign at present because in all of the places where the function is used there are incoming Tensor ORT_ENFORCE where it checks that the number of dimensions is greater than zero. I will fix this though.\r\n> @atp798 Do you have a specific example where this causes a crash?\r\n\r\nSorry, I haven't got one yet. I just read the code and found this.",
        "reactions": {
            "url": "https://api.github.com/repos/microsoft/onnxruntime/issues/comments/554612289/reactions",
            "total_count": 0,
            "+1": 0,
            "-1": 0,
            "laugh": 0,
            "hooray": 0,
            "confused": 0,
            "heart": 0,
            "rocket": 0,
            "eyes": 0
        },
        "performed_via_github_app": null,
        "event": "commented",
        "actor": {
            "login": "atp798",
            "id": 14136352,
            "node_id": "MDQ6VXNlcjE0MTM2MzUy",
            "avatar_url": "https://avatars.githubusercontent.com/u/14136352?v=4",
            "gravatar_id": "",
            "url": "https://api.github.com/users/atp798",
            "html_url": "https://github.com/atp798",
            "followers_url": "https://api.github.com/users/atp798/followers",
            "following_url": "https://api.github.com/users/atp798/following{/other_user}",
            "gists_url": "https://api.github.com/users/atp798/gists{/gist_id}",
            "starred_url": "https://api.github.com/users/atp798/starred{/owner}{/repo}",
            "subscriptions_url": "https://api.github.com/users/atp798/subscriptions",
            "organizations_url": "https://api.github.com/users/atp798/orgs",
            "repos_url": "https://api.github.com/users/atp798/repos",
            "events_url": "https://api.github.com/users/atp798/events{/privacy}",
            "received_events_url": "https://api.github.com/users/atp798/received_events",
            "type": "User",
            "site_admin": false
        }
    },
    {
        "id": 2804600235,
        "node_id": "MDE0Ok1lbnRpb25lZEV2ZW50MjgwNDYwMDIzNQ==",
        "url": "https://api.github.com/repos/microsoft/onnxruntime/issues/events/2804600235",
        "actor": {
            "login": "atp798",
            "id": 14136352,
            "node_id": "MDQ6VXNlcjE0MTM2MzUy",
            "avatar_url": "https://avatars.githubusercontent.com/u/14136352?v=4",
            "gravatar_id": "",
            "url": "https://api.github.com/users/atp798",
            "html_url": "https://github.com/atp798",
            "followers_url": "https://api.github.com/users/atp798/followers",
            "following_url": "https://api.github.com/users/atp798/following{/other_user}",
            "gists_url": "https://api.github.com/users/atp798/gists{/gist_id}",
            "starred_url": "https://api.github.com/users/atp798/starred{/owner}{/repo}",
            "subscriptions_url": "https://api.github.com/users/atp798/subscriptions",
            "organizations_url": "https://api.github.com/users/atp798/orgs",
            "repos_url": "https://api.github.com/users/atp798/repos",
            "events_url": "https://api.github.com/users/atp798/events{/privacy}",
            "received_events_url": "https://api.github.com/users/atp798/received_events",
            "type": "User",
            "site_admin": false
        },
        "event": "mentioned",
        "commit_id": null,
        "commit_url": null,
        "created_at": "2019-11-16T07:14:35Z",
        "performed_via_github_app": null
    },
    {
        "id": 2804600236,
        "node_id": "MDE1OlN1YnNjcmliZWRFdmVudDI4MDQ2MDAyMzY=",
        "url": "https://api.github.com/repos/microsoft/onnxruntime/issues/events/2804600236",
        "actor": {
            "login": "atp798",
            "id": 14136352,
            "node_id": "MDQ6VXNlcjE0MTM2MzUy",
            "avatar_url": "https://avatars.githubusercontent.com/u/14136352?v=4",
            "gravatar_id": "",
            "url": "https://api.github.com/users/atp798",
            "html_url": "https://github.com/atp798",
            "followers_url": "https://api.github.com/users/atp798/followers",
            "following_url": "https://api.github.com/users/atp798/following{/other_user}",
            "gists_url": "https://api.github.com/users/atp798/gists{/gist_id}",
            "starred_url": "https://api.github.com/users/atp798/starred{/owner}{/repo}",
            "subscriptions_url": "https://api.github.com/users/atp798/subscriptions",
            "organizations_url": "https://api.github.com/users/atp798/orgs",
            "repos_url": "https://api.github.com/users/atp798/repos",
            "events_url": "https://api.github.com/users/atp798/events{/privacy}",
            "received_events_url": "https://api.github.com/users/atp798/received_events",
            "type": "User",
            "site_admin": false
        },
        "event": "subscribed",
        "commit_id": null,
        "commit_url": null,
        "created_at": "2019-11-16T07:14:35Z",
        "performed_via_github_app": null
    },
    {
        "url": "https://api.github.com/repos/microsoft/onnxruntime/issues/comments/554800844",
        "html_url": "https://github.com/microsoft/onnxruntime/issues/2384#issuecomment-554800844",
        "issue_url": "https://api.github.com/repos/microsoft/onnxruntime/issues/2384",
        "id": 554800844,
        "node_id": "MDEyOklzc3VlQ29tbWVudDU1NDgwMDg0NA==",
        "user": {
            "login": "skottmckay",
            "id": 979079,
            "node_id": "MDQ6VXNlcjk3OTA3OQ==",
            "avatar_url": "https://avatars.githubusercontent.com/u/979079?v=4",
            "gravatar_id": "",
            "url": "https://api.github.com/users/skottmckay",
            "html_url": "https://github.com/skottmckay",
            "followers_url": "https://api.github.com/users/skottmckay/followers",
            "following_url": "https://api.github.com/users/skottmckay/following{/other_user}",
            "gists_url": "https://api.github.com/users/skottmckay/gists{/gist_id}",
            "starred_url": "https://api.github.com/users/skottmckay/starred{/owner}{/repo}",
            "subscriptions_url": "https://api.github.com/users/skottmckay/subscriptions",
            "organizations_url": "https://api.github.com/users/skottmckay/orgs",
            "repos_url": "https://api.github.com/users/skottmckay/repos",
            "events_url": "https://api.github.com/users/skottmckay/events{/privacy}",
            "received_events_url": "https://api.github.com/users/skottmckay/received_events",
            "type": "User",
            "site_admin": false
        },
        "created_at": "2019-11-17T23:34:49Z",
        "updated_at": "2019-11-17T23:34:49Z",
        "author_association": "MEMBER",
        "body": "> input_shape.Size() can return -1 as well to represent symbolic shapes. Check tensor_shape.cc.\r\n\r\nAlthough in this case it's calculating an output size, so the shape would be concrete with no symbolic dimensions.",
        "reactions": {
            "url": "https://api.github.com/repos/microsoft/onnxruntime/issues/comments/554800844/reactions",
            "total_count": 0,
            "+1": 0,
            "-1": 0,
            "laugh": 0,
            "hooray": 0,
            "confused": 0,
            "heart": 0,
            "rocket": 0,
            "eyes": 0
        },
        "performed_via_github_app": null,
        "event": "commented",
        "actor": {
            "login": "skottmckay",
            "id": 979079,
            "node_id": "MDQ6VXNlcjk3OTA3OQ==",
            "avatar_url": "https://avatars.githubusercontent.com/u/979079?v=4",
            "gravatar_id": "",
            "url": "https://api.github.com/users/skottmckay",
            "html_url": "https://github.com/skottmckay",
            "followers_url": "https://api.github.com/users/skottmckay/followers",
            "following_url": "https://api.github.com/users/skottmckay/following{/other_user}",
            "gists_url": "https://api.github.com/users/skottmckay/gists{/gist_id}",
            "starred_url": "https://api.github.com/users/skottmckay/starred{/owner}{/repo}",
            "subscriptions_url": "https://api.github.com/users/skottmckay/subscriptions",
            "organizations_url": "https://api.github.com/users/skottmckay/orgs",
            "repos_url": "https://api.github.com/users/skottmckay/repos",
            "events_url": "https://api.github.com/users/skottmckay/events{/privacy}",
            "received_events_url": "https://api.github.com/users/skottmckay/received_events",
            "type": "User",
            "site_admin": false
        }
    },
    {
        "url": "https://api.github.com/repos/microsoft/onnxruntime/issues/comments/554801450",
        "html_url": "https://github.com/microsoft/onnxruntime/issues/2384#issuecomment-554801450",
        "issue_url": "https://api.github.com/repos/microsoft/onnxruntime/issues/2384",
        "id": 554801450,
        "node_id": "MDEyOklzc3VlQ29tbWVudDU1NDgwMTQ1MA==",
        "user": {
            "login": "skottmckay",
            "id": 979079,
            "node_id": "MDQ6VXNlcjk3OTA3OQ==",
            "avatar_url": "https://avatars.githubusercontent.com/u/979079?v=4",
            "gravatar_id": "",
            "url": "https://api.github.com/users/skottmckay",
            "html_url": "https://github.com/skottmckay",
            "followers_url": "https://api.github.com/users/skottmckay/followers",
            "following_url": "https://api.github.com/users/skottmckay/following{/other_user}",
            "gists_url": "https://api.github.com/users/skottmckay/gists{/gist_id}",
            "starred_url": "https://api.github.com/users/skottmckay/starred{/owner}{/repo}",
            "subscriptions_url": "https://api.github.com/users/skottmckay/subscriptions",
            "organizations_url": "https://api.github.com/users/skottmckay/orgs",
            "repos_url": "https://api.github.com/users/skottmckay/repos",
            "events_url": "https://api.github.com/users/skottmckay/events{/privacy}",
            "received_events_url": "https://api.github.com/users/skottmckay/received_events",
            "type": "User",
            "site_admin": false
        },
        "created_at": "2019-11-17T23:42:04Z",
        "updated_at": "2019-11-17T23:42:04Z",
        "author_association": "MEMBER",
        "body": "@atp798 do you still think there's an issue?\r\n\r\nIf there are no dims in the shape it represents a scalar, so Size() returns 1.\r\nIf there are dims, at this point in execution there will be no symbolic dimensions so the value returned by Size() will not be negative, and generally will be > 0. \r\nThe edge case this check is handling is when a dimension has a value of 0, leading to Size() returning zero. This can happen for example if the first dimension represents the number of matches from a NonZero node. If that happens we know there are dimensions though, so accessing input_shape[0] is safe.\r\n\r\n",
        "reactions": {
            "url": "https://api.github.com/repos/microsoft/onnxruntime/issues/comments/554801450/reactions",
            "total_count": 0,
            "+1": 0,
            "-1": 0,
            "laugh": 0,
            "hooray": 0,
            "confused": 0,
            "heart": 0,
            "rocket": 0,
            "eyes": 0
        },
        "performed_via_github_app": null,
        "event": "commented",
        "actor": {
            "login": "skottmckay",
            "id": 979079,
            "node_id": "MDQ6VXNlcjk3OTA3OQ==",
            "avatar_url": "https://avatars.githubusercontent.com/u/979079?v=4",
            "gravatar_id": "",
            "url": "https://api.github.com/users/skottmckay",
            "html_url": "https://github.com/skottmckay",
            "followers_url": "https://api.github.com/users/skottmckay/followers",
            "following_url": "https://api.github.com/users/skottmckay/following{/other_user}",
            "gists_url": "https://api.github.com/users/skottmckay/gists{/gist_id}",
            "starred_url": "https://api.github.com/users/skottmckay/starred{/owner}{/repo}",
            "subscriptions_url": "https://api.github.com/users/skottmckay/subscriptions",
            "organizations_url": "https://api.github.com/users/skottmckay/orgs",
            "repos_url": "https://api.github.com/users/skottmckay/repos",
            "events_url": "https://api.github.com/users/skottmckay/events{/privacy}",
            "received_events_url": "https://api.github.com/users/skottmckay/received_events",
            "type": "User",
            "site_admin": false
        }
    },
    {
        "id": 2805784104,
        "node_id": "MDE0Ok1lbnRpb25lZEV2ZW50MjgwNTc4NDEwNA==",
        "url": "https://api.github.com/repos/microsoft/onnxruntime/issues/events/2805784104",
        "actor": {
            "login": "atp798",
            "id": 14136352,
            "node_id": "MDQ6VXNlcjE0MTM2MzUy",
            "avatar_url": "https://avatars.githubusercontent.com/u/14136352?v=4",
            "gravatar_id": "",
            "url": "https://api.github.com/users/atp798",
            "html_url": "https://github.com/atp798",
            "followers_url": "https://api.github.com/users/atp798/followers",
            "following_url": "https://api.github.com/users/atp798/following{/other_user}",
            "gists_url": "https://api.github.com/users/atp798/gists{/gist_id}",
            "starred_url": "https://api.github.com/users/atp798/starred{/owner}{/repo}",
            "subscriptions_url": "https://api.github.com/users/atp798/subscriptions",
            "organizations_url": "https://api.github.com/users/atp798/orgs",
            "repos_url": "https://api.github.com/users/atp798/repos",
            "events_url": "https://api.github.com/users/atp798/events{/privacy}",
            "received_events_url": "https://api.github.com/users/atp798/received_events",
            "type": "User",
            "site_admin": false
        },
        "event": "mentioned",
        "commit_id": null,
        "commit_url": null,
        "created_at": "2019-11-17T23:42:04Z",
        "performed_via_github_app": null
    },
    {
        "id": 2805784105,
        "node_id": "MDE1OlN1YnNjcmliZWRFdmVudDI4MDU3ODQxMDU=",
        "url": "https://api.github.com/repos/microsoft/onnxruntime/issues/events/2805784105",
        "actor": {
            "login": "atp798",
            "id": 14136352,
            "node_id": "MDQ6VXNlcjE0MTM2MzUy",
            "avatar_url": "https://avatars.githubusercontent.com/u/14136352?v=4",
            "gravatar_id": "",
            "url": "https://api.github.com/users/atp798",
            "html_url": "https://github.com/atp798",
            "followers_url": "https://api.github.com/users/atp798/followers",
            "following_url": "https://api.github.com/users/atp798/following{/other_user}",
            "gists_url": "https://api.github.com/users/atp798/gists{/gist_id}",
            "starred_url": "https://api.github.com/users/atp798/starred{/owner}{/repo}",
            "subscriptions_url": "https://api.github.com/users/atp798/subscriptions",
            "organizations_url": "https://api.github.com/users/atp798/orgs",
            "repos_url": "https://api.github.com/users/atp798/repos",
            "events_url": "https://api.github.com/users/atp798/events{/privacy}",
            "received_events_url": "https://api.github.com/users/atp798/received_events",
            "type": "User",
            "site_admin": false
        },
        "event": "subscribed",
        "commit_id": null,
        "commit_url": null,
        "created_at": "2019-11-17T23:42:04Z",
        "performed_via_github_app": null
    },
    {
        "id": 2805784165,
        "node_id": "MDE0OlVubGFiZWxlZEV2ZW50MjgwNTc4NDE2NQ==",
        "url": "https://api.github.com/repos/microsoft/onnxruntime/issues/events/2805784165",
        "actor": {
            "login": "skottmckay",
            "id": 979079,
            "node_id": "MDQ6VXNlcjk3OTA3OQ==",
            "avatar_url": "https://avatars.githubusercontent.com/u/979079?v=4",
            "gravatar_id": "",
            "url": "https://api.github.com/users/skottmckay",
            "html_url": "https://github.com/skottmckay",
            "followers_url": "https://api.github.com/users/skottmckay/followers",
            "following_url": "https://api.github.com/users/skottmckay/following{/other_user}",
            "gists_url": "https://api.github.com/users/skottmckay/gists{/gist_id}",
            "starred_url": "https://api.github.com/users/skottmckay/starred{/owner}{/repo}",
            "subscriptions_url": "https://api.github.com/users/skottmckay/subscriptions",
            "organizations_url": "https://api.github.com/users/skottmckay/orgs",
            "repos_url": "https://api.github.com/users/skottmckay/repos",
            "events_url": "https://api.github.com/users/skottmckay/events{/privacy}",
            "received_events_url": "https://api.github.com/users/skottmckay/received_events",
            "type": "User",
            "site_admin": false
        },
        "event": "unlabeled",
        "commit_id": null,
        "commit_url": null,
        "created_at": "2019-11-17T23:42:10Z",
        "label": {
            "name": "bug",
            "color": "d73a4a"
        },
        "performed_via_github_app": null
    },
    {
        "url": "https://api.github.com/repos/microsoft/onnxruntime/issues/comments/554828703",
        "html_url": "https://github.com/microsoft/onnxruntime/issues/2384#issuecomment-554828703",
        "issue_url": "https://api.github.com/repos/microsoft/onnxruntime/issues/2384",
        "id": 554828703,
        "node_id": "MDEyOklzc3VlQ29tbWVudDU1NDgyODcwMw==",
        "user": {
            "login": "atp798",
            "id": 14136352,
            "node_id": "MDQ6VXNlcjE0MTM2MzUy",
            "avatar_url": "https://avatars.githubusercontent.com/u/14136352?v=4",
            "gravatar_id": "",
            "url": "https://api.github.com/users/atp798",
            "html_url": "https://github.com/atp798",
            "followers_url": "https://api.github.com/users/atp798/followers",
            "following_url": "https://api.github.com/users/atp798/following{/other_user}",
            "gists_url": "https://api.github.com/users/atp798/gists{/gist_id}",
            "starred_url": "https://api.github.com/users/atp798/starred{/owner}{/repo}",
            "subscriptions_url": "https://api.github.com/users/atp798/subscriptions",
            "organizations_url": "https://api.github.com/users/atp798/orgs",
            "repos_url": "https://api.github.com/users/atp798/repos",
            "events_url": "https://api.github.com/users/atp798/events{/privacy}",
            "received_events_url": "https://api.github.com/users/atp798/received_events",
            "type": "User",
            "site_admin": false
        },
        "created_at": "2019-11-18T02:51:38Z",
        "updated_at": "2019-11-18T02:51:38Z",
        "author_association": "NONE",
        "body": "> @atp798 do you still think there's an issue?\r\n> \r\n> If there are no dims in the shape it represents a scalar, so Size() returns 1.\r\n> If there are dims, at this point in execution there will be no symbolic dimensions so the value returned by Size() will not be negative, and generally will be > 0.\r\n> The edge case this check is handling is when a dimension has a value of 0, leading to Size() returning zero. This can happen for example if the first dimension represents the number of matches from a NonZero node. If that happens we know there are dimensions though, so accessing input_shape[0] is safe.\r\n\r\nNo, I've got it.  Thank you & sorry for my carelessness.",
        "reactions": {
            "url": "https://api.github.com/repos/microsoft/onnxruntime/issues/comments/554828703/reactions",
            "total_count": 0,
            "+1": 0,
            "-1": 0,
            "laugh": 0,
            "hooray": 0,
            "confused": 0,
            "heart": 0,
            "rocket": 0,
            "eyes": 0
        },
        "performed_via_github_app": null,
        "event": "commented",
        "actor": {
            "login": "atp798",
            "id": 14136352,
            "node_id": "MDQ6VXNlcjE0MTM2MzUy",
            "avatar_url": "https://avatars.githubusercontent.com/u/14136352?v=4",
            "gravatar_id": "",
            "url": "https://api.github.com/users/atp798",
            "html_url": "https://github.com/atp798",
            "followers_url": "https://api.github.com/users/atp798/followers",
            "following_url": "https://api.github.com/users/atp798/following{/other_user}",
            "gists_url": "https://api.github.com/users/atp798/gists{/gist_id}",
            "starred_url": "https://api.github.com/users/atp798/starred{/owner}{/repo}",
            "subscriptions_url": "https://api.github.com/users/atp798/subscriptions",
            "organizations_url": "https://api.github.com/users/atp798/orgs",
            "repos_url": "https://api.github.com/users/atp798/repos",
            "events_url": "https://api.github.com/users/atp798/events{/privacy}",
            "received_events_url": "https://api.github.com/users/atp798/received_events",
            "type": "User",
            "site_admin": false
        }
    },
    {
        "id": 2805978368,
        "node_id": "MDE0Ok1lbnRpb25lZEV2ZW50MjgwNTk3ODM2OA==",
        "url": "https://api.github.com/repos/microsoft/onnxruntime/issues/events/2805978368",
        "actor": {
            "login": "atp798",
            "id": 14136352,
            "node_id": "MDQ6VXNlcjE0MTM2MzUy",
            "avatar_url": "https://avatars.githubusercontent.com/u/14136352?v=4",
            "gravatar_id": "",
            "url": "https://api.github.com/users/atp798",
            "html_url": "https://github.com/atp798",
            "followers_url": "https://api.github.com/users/atp798/followers",
            "following_url": "https://api.github.com/users/atp798/following{/other_user}",
            "gists_url": "https://api.github.com/users/atp798/gists{/gist_id}",
            "starred_url": "https://api.github.com/users/atp798/starred{/owner}{/repo}",
            "subscriptions_url": "https://api.github.com/users/atp798/subscriptions",
            "organizations_url": "https://api.github.com/users/atp798/orgs",
            "repos_url": "https://api.github.com/users/atp798/repos",
            "events_url": "https://api.github.com/users/atp798/events{/privacy}",
            "received_events_url": "https://api.github.com/users/atp798/received_events",
            "type": "User",
            "site_admin": false
        },
        "event": "mentioned",
        "commit_id": null,
        "commit_url": null,
        "created_at": "2019-11-18T02:51:40Z",
        "performed_via_github_app": null
    },
    {
        "id": 2805978371,
        "node_id": "MDE1OlN1YnNjcmliZWRFdmVudDI4MDU5NzgzNzE=",
        "url": "https://api.github.com/repos/microsoft/onnxruntime/issues/events/2805978371",
        "actor": {
            "login": "atp798",
            "id": 14136352,
            "node_id": "MDQ6VXNlcjE0MTM2MzUy",
            "avatar_url": "https://avatars.githubusercontent.com/u/14136352?v=4",
            "gravatar_id": "",
            "url": "https://api.github.com/users/atp798",
            "html_url": "https://github.com/atp798",
            "followers_url": "https://api.github.com/users/atp798/followers",
            "following_url": "https://api.github.com/users/atp798/following{/other_user}",
            "gists_url": "https://api.github.com/users/atp798/gists{/gist_id}",
            "starred_url": "https://api.github.com/users/atp798/starred{/owner}{/repo}",
            "subscriptions_url": "https://api.github.com/users/atp798/subscriptions",
            "organizations_url": "https://api.github.com/users/atp798/orgs",
            "repos_url": "https://api.github.com/users/atp798/repos",
            "events_url": "https://api.github.com/users/atp798/events{/privacy}",
            "received_events_url": "https://api.github.com/users/atp798/received_events",
            "type": "User",
            "site_admin": false
        },
        "event": "subscribed",
        "commit_id": null,
        "commit_url": null,
        "created_at": "2019-11-18T02:51:40Z",
        "performed_via_github_app": null
    },
    {
        "id": 2805978427,
        "node_id": "MDExOkNsb3NlZEV2ZW50MjgwNTk3ODQyNw==",
        "url": "https://api.github.com/repos/microsoft/onnxruntime/issues/events/2805978427",
        "actor": {
            "login": "atp798",
            "id": 14136352,
            "node_id": "MDQ6VXNlcjE0MTM2MzUy",
            "avatar_url": "https://avatars.githubusercontent.com/u/14136352?v=4",
            "gravatar_id": "",
            "url": "https://api.github.com/users/atp798",
            "html_url": "https://github.com/atp798",
            "followers_url": "https://api.github.com/users/atp798/followers",
            "following_url": "https://api.github.com/users/atp798/following{/other_user}",
            "gists_url": "https://api.github.com/users/atp798/gists{/gist_id}",
            "starred_url": "https://api.github.com/users/atp798/starred{/owner}{/repo}",
            "subscriptions_url": "https://api.github.com/users/atp798/subscriptions",
            "organizations_url": "https://api.github.com/users/atp798/orgs",
            "repos_url": "https://api.github.com/users/atp798/repos",
            "events_url": "https://api.github.com/users/atp798/events{/privacy}",
            "received_events_url": "https://api.github.com/users/atp798/received_events",
            "type": "User",
            "site_admin": false
        },
        "event": "closed",
        "commit_id": null,
        "commit_url": null,
        "created_at": "2019-11-18T02:51:41Z",
        "state_reason": null,
        "performed_via_github_app": null
    }
]