[
    {
        "url": "https://api.github.com/repos/microsoft/onnxruntime/issues/comments/1265523102",
        "html_url": "https://github.com/microsoft/onnxruntime/issues/12009#issuecomment-1265523102",
        "issue_url": "https://api.github.com/repos/microsoft/onnxruntime/issues/12009",
        "id": 1265523102,
        "node_id": "IC_kwDOCVq1mM5Lblme",
        "user": {
            "login": "FRidh",
            "id": 2129135,
            "node_id": "MDQ6VXNlcjIxMjkxMzU=",
            "avatar_url": "https://avatars.githubusercontent.com/u/2129135?v=4",
            "gravatar_id": "",
            "url": "https://api.github.com/users/FRidh",
            "html_url": "https://github.com/FRidh",
            "followers_url": "https://api.github.com/users/FRidh/followers",
            "following_url": "https://api.github.com/users/FRidh/following{/other_user}",
            "gists_url": "https://api.github.com/users/FRidh/gists{/gist_id}",
            "starred_url": "https://api.github.com/users/FRidh/starred{/owner}{/repo}",
            "subscriptions_url": "https://api.github.com/users/FRidh/subscriptions",
            "organizations_url": "https://api.github.com/users/FRidh/orgs",
            "repos_url": "https://api.github.com/users/FRidh/repos",
            "events_url": "https://api.github.com/users/FRidh/events{/privacy}",
            "received_events_url": "https://api.github.com/users/FRidh/received_events",
            "type": "User",
            "site_admin": false
        },
        "created_at": "2022-10-03T14:24:37Z",
        "updated_at": "2022-10-03T14:24:37Z",
        "author_association": "NONE",
        "body": "In Nixpkgs we aim to maintain a set of compatible Python packages. `protobuf` can be used as runtime dependency, which means we support at most one versions of `protobuf`. It's therefore important that packages can work with multiple versions of `protobuf` so it is possible to support a coherent package set.\r\n\r\nRelated issues:\r\n- https://github.com/microsoft/onnxruntime/issues/13053\r\n- https://github.com/NixOS/nixpkgs/pull/194111",
        "reactions": {
            "url": "https://api.github.com/repos/microsoft/onnxruntime/issues/comments/1265523102/reactions",
            "total_count": 0,
            "+1": 0,
            "-1": 0,
            "laugh": 0,
            "hooray": 0,
            "confused": 0,
            "heart": 0,
            "rocket": 0,
            "eyes": 0
        },
        "performed_via_github_app": null
    },
    {
        "url": "https://api.github.com/repos/microsoft/onnxruntime/issues/comments/1309497018",
        "html_url": "https://github.com/microsoft/onnxruntime/issues/12009#issuecomment-1309497018",
        "issue_url": "https://api.github.com/repos/microsoft/onnxruntime/issues/12009",
        "id": 1309497018,
        "node_id": "IC_kwDOCVq1mM5ODVa6",
        "user": {
            "login": "devalexqt",
            "id": 865007,
            "node_id": "MDQ6VXNlcjg2NTAwNw==",
            "avatar_url": "https://avatars.githubusercontent.com/u/865007?v=4",
            "gravatar_id": "",
            "url": "https://api.github.com/users/devalexqt",
            "html_url": "https://github.com/devalexqt",
            "followers_url": "https://api.github.com/users/devalexqt/followers",
            "following_url": "https://api.github.com/users/devalexqt/following{/other_user}",
            "gists_url": "https://api.github.com/users/devalexqt/gists{/gist_id}",
            "starred_url": "https://api.github.com/users/devalexqt/starred{/owner}{/repo}",
            "subscriptions_url": "https://api.github.com/users/devalexqt/subscriptions",
            "organizations_url": "https://api.github.com/users/devalexqt/orgs",
            "repos_url": "https://api.github.com/users/devalexqt/repos",
            "events_url": "https://api.github.com/users/devalexqt/events{/privacy}",
            "received_events_url": "https://api.github.com/users/devalexqt/received_events",
            "type": "User",
            "site_admin": false
        },
        "created_at": "2022-11-09T22:52:53Z",
        "updated_at": "2022-11-09T22:52:53Z",
        "author_association": "NONE",
        "body": "```\r\npip3.9 install --force-reinstall onnxruntime-gpu\r\n```\r\n```\r\nERROR: pip's dependency resolver does not currently take into account all the packages that are installed. This behaviour is the source of the following dependency conflicts.\r\nonnx 1.12.0 requires protobuf<=3.20.1,>=3.12.2, but you have protobuf 4.21.9 which is incompatible.\r\n```",
        "reactions": {
            "url": "https://api.github.com/repos/microsoft/onnxruntime/issues/comments/1309497018/reactions",
            "total_count": 0,
            "+1": 0,
            "-1": 0,
            "laugh": 0,
            "hooray": 0,
            "confused": 0,
            "heart": 0,
            "rocket": 0,
            "eyes": 0
        },
        "performed_via_github_app": null
    },
    {
        "url": "https://api.github.com/repos/microsoft/onnxruntime/issues/comments/1489060052",
        "html_url": "https://github.com/microsoft/onnxruntime/issues/12009#issuecomment-1489060052",
        "issue_url": "https://api.github.com/repos/microsoft/onnxruntime/issues/12009",
        "id": 1489060052,
        "node_id": "IC_kwDOCVq1mM5YwUDU",
        "user": {
            "login": "michael-newsrx",
            "id": 5214185,
            "node_id": "MDQ6VXNlcjUyMTQxODU=",
            "avatar_url": "https://avatars.githubusercontent.com/u/5214185?v=4",
            "gravatar_id": "",
            "url": "https://api.github.com/users/michael-newsrx",
            "html_url": "https://github.com/michael-newsrx",
            "followers_url": "https://api.github.com/users/michael-newsrx/followers",
            "following_url": "https://api.github.com/users/michael-newsrx/following{/other_user}",
            "gists_url": "https://api.github.com/users/michael-newsrx/gists{/gist_id}",
            "starred_url": "https://api.github.com/users/michael-newsrx/starred{/owner}{/repo}",
            "subscriptions_url": "https://api.github.com/users/michael-newsrx/subscriptions",
            "organizations_url": "https://api.github.com/users/michael-newsrx/orgs",
            "repos_url": "https://api.github.com/users/michael-newsrx/repos",
            "events_url": "https://api.github.com/users/michael-newsrx/events{/privacy}",
            "received_events_url": "https://api.github.com/users/michael-newsrx/received_events",
            "type": "User",
            "site_admin": false
        },
        "created_at": "2023-03-29T18:00:35Z",
        "updated_at": "2023-03-29T18:00:49Z",
        "author_association": "NONE",
        "body": "```python\r\nInstalling collected packages: protobuf\r\n  Attempting uninstall: protobuf\r\n    Found existing installation: protobuf 3.20.3\r\n    Uninstalling protobuf-3.20.3:\r\n      Successfully uninstalled protobuf-3.20.3\r\nERROR: pip's dependency resolver does not currently take into account all the packages that are installed. This behaviour is the source of the following dependency conflicts.\r\ntensorflow 2.12.0 requires protobuf!=4.21.0,!=4.21.1,!=4.21.2,!=4.21.3,!=4.21.4,!=4.21.5,<5.0.0dev,>=3.20.3, but you have protobuf 3.20.2 which is incompatible.\r\n```",
        "reactions": {
            "url": "https://api.github.com/repos/microsoft/onnxruntime/issues/comments/1489060052/reactions",
            "total_count": 0,
            "+1": 0,
            "-1": 0,
            "laugh": 0,
            "hooray": 0,
            "confused": 0,
            "heart": 0,
            "rocket": 0,
            "eyes": 0
        },
        "performed_via_github_app": null
    }
]