[
    {
        "id": 8218050701,
        "node_id": "LE_lADOCVq1mM5bTfEbzwAAAAHp1YCN",
        "url": "https://api.github.com/repos/microsoft/onnxruntime/issues/events/8218050701",
        "actor": {
            "login": "dawei03896",
            "id": 84013536,
            "node_id": "MDQ6VXNlcjg0MDEzNTM2",
            "avatar_url": "https://avatars.githubusercontent.com/u/84013536?v=4",
            "gravatar_id": "",
            "url": "https://api.github.com/users/dawei03896",
            "html_url": "https://github.com/dawei03896",
            "followers_url": "https://api.github.com/users/dawei03896/followers",
            "following_url": "https://api.github.com/users/dawei03896/following{/other_user}",
            "gists_url": "https://api.github.com/users/dawei03896/gists{/gist_id}",
            "starred_url": "https://api.github.com/users/dawei03896/starred{/owner}{/repo}",
            "subscriptions_url": "https://api.github.com/users/dawei03896/subscriptions",
            "organizations_url": "https://api.github.com/users/dawei03896/orgs",
            "repos_url": "https://api.github.com/users/dawei03896/repos",
            "events_url": "https://api.github.com/users/dawei03896/events{/privacy}",
            "received_events_url": "https://api.github.com/users/dawei03896/received_events",
            "type": "User",
            "site_admin": false
        },
        "event": "labeled",
        "commit_id": null,
        "commit_url": null,
        "created_at": "2023-01-13T07:24:53Z",
        "label": {
            "name": "feature request",
            "color": "5319E7"
        },
        "performed_via_github_app": null
    }
]